waterfalls/__init__.py
waterfalls/timer.py
waterfalls/viewer.py
waterfalls-0.2.1.dist-info/entry_points.txt
waterfalls-0.2.1.dist-info/LICENSE
waterfalls-0.2.1.dist-info/WHEEL
waterfalls-0.2.1.dist-info/METADATA
waterfalls-0.2.1.dist-info/RECORD
