Metadata-Version: 2.1
Name: waterfalls
Version: 0.2.1
Summary: Visualizes duration and CPU usage of blocks of code to let you see bottlenecks in your applications.
License: MIT
Keywords: timing,diagrams
Author: Glen Vorel
Author-email: glen.vorel@gmail.com
Requires-Python: >=3.8,<4.0
Classifier: License :: OSI Approved :: MIT License
Classifier: Programming Language :: Python :: 3
Classifier: Programming Language :: Python :: 3.10
Classifier: Programming Language :: Python :: 3.8
Classifier: Programming Language :: Python :: 3.9
Requires-Dist: matplotlib (>=3.5.1,<4.0.0)
